cloudshell/__init__.py
cloudshell/raritan/__init__.py
cloudshell/raritan/autoload/__init__.py
cloudshell/raritan/cli/__init__.py
cloudshell/raritan/cli/raritan_cli_configurator.py
cloudshell/raritan/cli/raritan_command_modes.py
cloudshell/raritan/cli/raritan_ssh_session.py
cloudshell/raritan/cli/raritan_telnet_session.py
cloudshell/raritan/command_actions/__init__.py
cloudshell/raritan/command_actions/enable_disable_snmp_actions.py
cloudshell/raritan/command_actions/system_actions.py
cloudshell/raritan/command_templates/__init__.py
cloudshell/raritan/command_templates/snmp_configuration_templates.py
cloudshell/raritan/command_templates/system_templates.py
cloudshell/raritan/flows/__init__.py
cloudshell/raritan/flows/raritan_autoload_flow.py
cloudshell/raritan/flows/raritan_enable_disable_snmp_flow.py
cloudshell/raritan/flows/raritan_outlets_state_flow.py
cloudshell/raritan/helpers/__init__.py
cloudshell/raritan/helpers/errors.py
tests/__init__.py
tests/cloudshell/__init__.py
tests/cloudshell/raritan/__init__.py
tests/cloudshell/raritan/command_actions/__init__.py
tests/cloudshell/raritan/command_actions/test_system_actions.py
cloudshell_raritan-1.0.2.dist-info/METADATA
cloudshell_raritan-1.0.2.dist-info/WHEEL
cloudshell_raritan-1.0.2.dist-info/top_level.txt
cloudshell_raritan-1.0.2.dist-info/RECORD
